ratelimitapi/__init__.py
ratelimitapi/ratelimit.py
ratelimitapi-0.1.1.dist-info/licenses/LICENSE
ratelimitapi-0.1.1.dist-info/METADATA
ratelimitapi-0.1.1.dist-info/WHEEL
ratelimitapi-0.1.1.dist-info/top_level.txt
ratelimitapi-0.1.1.dist-info/RECORD
